test/test_hybrid_attn.py
test/test_hybrid_qkvpacked_attn.py
test/test_ulysses_attn.py
test/test_utils.py
yunchang/__init__.py
yunchang/globals.py
yunchang/comm/__init__.py
yunchang/comm/all_to_all.py
yunchang/comm/extract_local.py
yunchang/hybrid/__init__.py
yunchang/hybrid/async_attn_layer.py
yunchang/hybrid/attn_layer.py
yunchang/hybrid/utils.py
yunchang/kernels/__init__.py
yunchang/kernels/attention.py
yunchang/ring/__init__.py
yunchang/ring/ring_flash_attn.py
yunchang/ring/ring_flash_attn_varlen.py
yunchang/ring/ring_flashinfer_attn.py
yunchang/ring/ring_pytorch_attn.py
yunchang/ring/stripe_flash_attn.py
yunchang/ring/triton_utils.py
yunchang/ring/utils.py
yunchang/ring/zigzag_ring_flash_attn.py
yunchang/ring/zigzag_ring_flash_attn_varlen.py
yunchang/ulysses/__init__.py
yunchang/ulysses/attn_layer.py
yunchang-0.6.3.dist-info/licenses/LICENSE.txt
yunchang-0.6.3.dist-info/METADATA
yunchang-0.6.3.dist-info/WHEEL
yunchang-0.6.3.dist-info/top_level.txt
yunchang-0.6.3.dist-info/RECORD
