Metadata-Version: 2.4
Name: yunchang
Version: 0.6.3
Summary: a package for long context attention
Author-email: Jiarui Fang <fangjiarui123@gmail.com>
Project-URL: Homepage, https://github.com/feifeibear/long-context-attention
Project-URL: Bug Tracker, https://github.com/feifeibear/long-context-attention/issues
Classifier: Programming Language :: Python :: 3
Classifier: License :: OSI Approved :: Apache Software License
Classifier: Operating System :: OS Independent
Requires-Python: >=3.7
License-File: LICENSE.txt
Provides-Extra: flash
Requires-Dist: flash-attn>=2.6.0; extra == "flash"
Dynamic: license-file
